{"_id":"5b1614a16f1f271c06005e30","screening":{"status":1,"history":[]},"ethicalStatus":{"hasValue":false},"childrenCount":{"topics":{"total":0,"accepted":0,"pending":0,"rejected":0},"artifacts":{"total":0,"accepted":0,"pending":0,"rejected":0},"arguments":{"total":0,"accepted":0,"pending":0,"rejected":0},"questions":{"total":0,"accepted":0,"pending":0,"rejected":0},"issues":{"total":0,"accepted":0,"pending":0,"rejected":0,"acceptedCritical":0},"opinions":{"total":0,"accepted":0,"pending":0,"rejected":0}},"title":"topic 2 on group 8","content":"<p>abc</p>","references":"","topicTags":[],"parentId":null,"groupId":"5ab241108240b818fd715eda","ownerId":"5ab241108240b818fd715eda","ownerType":30,"tags":[],"private":true,"__v":0,"outline":[],"sharing":{"users":[]},"categoryId":null,"createDate":"2018-06-05T04:42:09.204Z","createUserId":"561b43d499a0478551eab839","icon":"","referenceDate":null,"editDate":"2018-06-05T04:42:09.204Z","editUserId":"561b43d499a0478551eab839","friendlyUrl":"topic-2-on-group-8","contextTitle":"","contentPreview":"abc"}