{"_id":"57ea42a9777336a5ad09a5bf","parentId":"57a8d2c4c2e743a60661318f","createDate":"2016-09-27T09:58:01.893Z","createUserId":"561b43d499a0478551eab839","ethicalStatus":{"hasValue":false},"icon":"","editDate":"2016-09-27T09:58:01.893Z","editUserId":"561b43d499a0478551eab839","references":"","contextTitle":"","title":"a sub sub topic","content":"","childrenCount":{"arguments":0,"opinions":0,"issues":1,"topics":0,"questions":0},"outline":[],"private":false,"screeningStatus":0,"tags":[],"ownerType":-1,"ownerId":null}